{
  "entity": [
    {
      "id": 0,
      "posX": 6572.75145049765,
      "posY": 8354.719656561028,
      "posZ": 0.0,
      "type": "Unit"
    },
    {
      "id": 1,
      "posX": 5016.346666326549,
      "posY": 5360.3352380466495,
      "posZ": 0.0,
      "type": "Unit"
    },
    {
      "id": 2,
      "posX": 1833.429978208661,
      "posY": 4658.429978208661,
      "posZ": 0.0,
      "type": "Unit"
    },
    {
      "id": 3,
      "posX": 9390.863527754791,
      "posY": 9407.863527754791,
      "posZ": 0.0,
      "type": "Unit"
    },
    {
      "id": 4,
      "posX": 9667.401782533972,
      "posY": 3405.3515597172272,
      "posZ": 0.0,
      "type": "Unit"
    },
    {
      "id": 5,
      "posX": 2956.07295521008,
      "posY": 8465.527880560214,
      "posZ": 0.0,
      "type": "Unit"
    },
    {
      "id": 6,
      "posX": 1228.6853429081534,
      "posY": 4758.561780969383,
      "posZ": 0.0,
      "type": "Unit"
    },
    {
      "id": 7,
      "posX": 6322.363457525985,
      "posY": 7811.72691505197,
      "posZ": 0.0,
      "type": "Unit"
    },
    {
      "id": 8,
      "posX": 7846.322621173093,
      "posY": 9368.193447067271,
      "posZ": 0.0,
      "type": "Unit"
    },
    {
      "id": 9,
      "posX": 7758.050865276332,
      "posY": 452.0508652763321,
      "posZ": 0.0,
      "type": "Unit"
    },
    {
      "id": 10,
      "posX": 7105.60646988095,
      "posY": 927.3032349404751,
      "posZ": 0.0,
      "type": "Unit"
    },
    {
      "id": 11,
      "posX": 680.8367634335027,
      "posY": 8416.183817167514,
      "posZ": 0.0,
      "type": "Unit"
    },
    {
      "id": 12,
      "posX": 2619.5999999999995,
      "posY": 8755.199999999999,
      "posZ": 0.0,
      "type": "Unit"
    },
    {
      "id": 13,
      "posX": 8775.646242019637,
      "posY": 1428.8774521178148,
      "posZ": 0.0,
      "type": "Unit"
    },
    {
      "id": 14,
      "posX": 5819.521933170094,
      "posY": 1772.8406443900317,
      "posZ": 0.0,
      "type": "Unit"
    },
    {
      "id": 15,
      "posX": 5877.274681864115,
      "posY": 6692.129618236938,
      "posZ": 0.0,
      "type": "Unit"
    },
    {
      "id": 16,
      "posX": 3020.0,
      "posY": 7984.0,
      "posZ": 0.0,
      "type": "Unit"
    },
    {
      "id": 17,
      "posX": 9300.055037461232,
      "posY": 638.9043178239137,
      "posZ": 0.0,
      "type": "Unit"
    },
    {
      "id": 18,
      "posX": 7058.562012564626,
      "posY": 9832.187337521542,
      "posZ": 0.0,
      "type": "Unit"
    },
    {
      "id": 19,
      "posX": 1951.1357448663287,
      "posY": 5683.678724331641,
      "posZ": 0.0,
      "type": "Unit"
    },
    {
      "id": 20,
      "posX": 8935.0,
      "posY": 8922.0,
      "posZ": 0.0,
      "type": "Unit"
    },
    {
      "id": 21,
      "posX": 1154.955410846827,
      "posY": 6650.955410846828,
      "posZ": 0.0,
      "type": "Unit"
    },
    {
      "id": 22,
      "posX": 7996.0,
      "posY": 5560.0,
      "posZ": 0.0,
      "type": "Unit"
    },
    {
      "id": 23,
      "posX": 8133.885129674721,
      "posY": 8589.081037397766,
      "posZ": 0.0,
      "type": "Unit"
    },
    {
      "id": 24,
      "posX": 784.0,
      "posY": 3866.0,
      "posZ": 0.0,
      "type": "Unit"
    },
    {
      "id": 25,
      "posX": 1333.7999999999997,
      "posY": 4823.5999999999995,
      "posZ": 0.0,
      "type": "Unit"
    },
    {
      "id": 26,
      "posX": 6578.688706539019,
      "posY": 6798.275482615609,
      "posZ": 0.0,
      "type": "Unit"
    },
    {
      "id": 27,
      "posX": 2512.243092815946,
      "posY": 2125.5944742527563,
      "posZ": 0.0,
      "type": "Unit"
    },
    {
      "id": 28,
      "posX": 363.6676628396946,
      "posY": 7666.934130271755,
      "posZ": 0.0,
      "type": "Unit"
    },
    {
      "id": 29,
      "posX": 4669.0,
      "posY": 5550.0,
      "posZ": 0.0,
      "type": "Unit"
    },
    {
      "id": 30,
      "posX": 9496.0,
      "posY": 5345.0,
      "posZ": 0.0,
      "type": "Unit"
    },
    {
      "id": 31,
      "posX": 9265.0,
      "posY": 7168.0,
      "posZ": 0.0,
      "type": "Unit"
    },
    {
      "id": 32,
      "posX": 3334.969237519619,
      "posY": 1632.8769500784792,
      "posZ": 0.0,
      "type": "Unit"
    },
    {
      "id": 33,
      "posX": 6721.263768087985,
      "posY": 6329.131884043993,
      "posZ": 0.0,
      "type": "Unit"
    },
    {
      "id": 34,
      "posX": 4473.0,
      "posY": 3750.0,
      "posZ": 0.0,
      "type": "Unit"
    },
    {
      "id": 35,
      "posX": 4621.709198822239,
      "posY": 8467.709198822242,
      "posZ": 0.0,
      "type": "Unit"
    },
    {
      "id": 36,
      "posX": 8308.716341497175,
      "posY": 1469.716341497176,
      "posZ": 0.0,
      "type": "Unit"
    },
    {
      "id": 37,
      "posX": 1063.2253622419612,
      "posY": 5052.61268112098,
      "posZ": 0.0,
      "type": "Unit"
    },
    {
      "id": 38,
      "posX": 8963.256094188107,
      "posY": 9480.615858717836,
      "posZ": 0.0,
      "type": "Unit"
    },
    {
      "id": 39,
      "posX": 1963.7195075764064,
      "posY": 3208.631704545843,
      "posZ": 0.0,
      "type": "Unit"
    },
    {
      "id": 40,
      "posX": 1302.776550292767,
      "posY": 4241.665614536657,
      "posZ": 0.0,
      "type": "Unit"
    },
    {
      "id": 41,
      "posX": 6447.656350548177,
      "posY": 596.1486134593118,
      "posZ": 0.0,
      "type": "Unit"
    },
    {
      "id": 42,
      "posX": 9784.25418370423,
      "posY": 5241.27091852115,
      "posZ": 0.0,
      "type": "Unit"
    },
    {
      "id": 43,
      "posX": 1982.7184106734132,
      "posY": 6131.342958237963,
      "posZ": 0.0,
      "type": "Unit"
    },
    {
      "id": 44,
      "posX": 9149.02765994967,
      "posY": 1089.2331919396063,
      "posZ": 0.0,
      "type": "Unit"
    },
    {
      "id": 45,
      "posX": 4597.248395954138,
      "posY": 4665.872593931205,
      "posZ": 0.0,
      "type": "Unit"
    },
    {
      "id": 46,
      "posX": 971.2139177030901,
      "posY": 1140.4974239216303,
      "posZ": 0.0,
      "type": "Unit"
    },
    {
      "id": 47,
      "posX": 6926.721522799684,
      "posY": 2581.772182397473,
      "posZ": 0.0,
      "type": "Unit"
    },
    {
      "id": 48,
      "posX": 8355.599570260185,
      "posY": 1234.3490330854188,
      "posZ": 0.0,
      "type": "Unit"
    },
    {
      "id": 49,
      "posX": 750.0,
      "posY": 4934.0,
      "posZ": 0.0,
      "type": "Unit"
    },
    {
      "id": 50,
      "posX": 5974.999569583177,
      "posY": 6986.498063124301,
      "posZ": 0.0,
      "type": "Unit"
    },
    {
      "id": 51,
      "posX": 1766.3571107880425,
      "posY": 6262.874943879074,
      "posZ": 0.0,
      "type": "Unit"
    },
    {
      "id": 52,
      "posX": 5380.0,
      "posY": 2910.0,
      "posZ": 0.0,
      "type": "Unit"
    },
    {
      "id": 53,
      "posX": 7668.24994258153,
      "posY": 8540.062485645383,
      "posZ": 0.0,
      "type": "Unit"
    },
    {
      "id": 54,
      "posX": 7587.998642529213,
      "posY": 804.7496606323028,
      "posZ": 0.0,
      "type": "Unit"
    },
    {
      "id": 55,
      "posX": 7167.238500127394,
      "posY": 685.0209287352213,
      "posZ": 0.0,
      "type": "Unit"
    },
    {
      "id": 56,
      "posX": 846.0,
      "posY": 4895.0,
      "posZ": 0.0,
      "type": "Unit"
    },
    {
      "id": 57,
      "posX": 2300.8898800379084,
      "posY": 4116.494377798838,
      "posZ": 0.0,
      "type": "Unit"
    },
    {
      "id": 58,
      "posX": 1026.8,
      "posY": 4008.5999999999995,
      "posZ": 0.0,
      "type": "Unit"
    },
    {
      "id": 59,
      "posX": 4426.793525540078,
      "posY": 430.07086493035223,
      "posZ": 0.0,
      "type": "Unit"
    },
    {
      "id": 60,
      "posX": 6306.27991948634,
      "posY": 2574.2393558907165,
      "posZ": 0.0,
      "type": "Unit"
    },
    {
      "id": 61,
      "posX": 4673.678840948401,
      "posY": 439.62774353457155,
      "posZ": 0.0,
      "type": "Unit"
    },
    {
      "id": 62,
      "posX": 4252.621037570221,
      "posY": 207.12420751404406,
      "posZ": 0.0,
      "type": "Unit"
    },
    {
      "id": 63,
      "posX": 4681.310518785111,
      "posY": 9262.552593925548,
      "posZ": 0.0,
      "type": "Unit"
    },
    {
      "id": 64,
      "posX": 4611.899505422264,
      "posY": 9396.432179318612,
      "posZ": 0.0,
      "type": "Unit"
    },
    {
      "id": 65,
      "posX": 4082.0,
      "posY": 8212.0,
      "posZ": 0.0,
      "type": "Unit"
    },
    {
      "id": 66,
      "posX": 6102.167633665098,
      "posY": 9321.479771040686,
      "posZ": 0.0,
      "type": "Unit"
    },
    {
      "id": 67,
      "posX": 7932.040680336406,
      "posY": 719.4625245939584,
      "posZ": 0.0,
      "type": "Unit"
    },
    {
      "id": 68,
      "posX": 9292.276908973454,
      "posY": 9167.808779120103,
      "posZ": 0.0,
      "type": "Unit"
    },
    {
      "id": 69,
      "posX": 2809.1851947190603,
      "posY": 8067.296363033426,
      "posZ": 0.0,
      "type": "Unit"
    },
    {
      "id": 70,
      "posX": 1860.779865390983,
      "posY": 3492.8899326954916,
      "posZ": 0.0,
      "type": "Unit"
    },
    {
      "id": 71,
      "posX": 8392.108022690958,
      "posY": 8366.054011345477,
      "posZ": 0.0,
      "type": "Unit"
    },
    {
      "id": 72,
      "posX": 5957.8052384954135,
      "posY": 8783.849429291742,
      "posZ": 0.0,
      "type": "Unit"
    },
    {
      "id": 73,
      "posX": 1334.0925791691488,
      "posY": 226.3310067730054,
      "posZ": 0.0,
      "type": "Unit"
    },
    {
      "id": 74,
      "posX": 9993.786354317343,
      "posY": 6790.044882869004,
      "posZ": 0.0,
      "type": "Unit"
    },
    {
      "id": 75,
      "posX": 7938.6770742087365,
      "posY": 5225.69268552184,
      "posZ": 0.0,
      "type": "Unit"
    },
    {
      "id": 76,
      "posX": 5714.289934625983,
      "posY": 2621.289934625983,
      "posZ": 0.0,
      "type": "Unit"
    },
    {
      "id": 77,
      "posX": 4751.4000000000005,
      "posY": 1355.7999999999997,
      "posZ": 0.0,
      "type": "Unit"
    },
    {
      "id": 78,
      "posX": 5417.011438872975,
      "posY": 3760.5057194364877,
      "posZ": 0.0,
      "type": "Unit"
    },
    {
      "id": 79,
      "posX": 4187.536146650571,
      "posY": 9525.53614665057,
      "posZ": 0.0,
      "type": "Unit"
    },
    {
      "id": 80,
      "posX": 9418.410058867566,
      "posY": 3300.6150883013524,
      "posZ": 0.0,
      "type": "Unit"
    },
    {
      "id": 81,
      "posX": 3670.1348236946383,
      "posY": 440.40823538591013,
      "posZ": 0.0,
      "type": "Unit"
    },
    {
      "id": 82,
      "posX": 1732.7056274847714,
      "posY": 1752.7056274847714,
      "posZ": 0.0,
      "type": "Unit"
    },
    {
      "id": 83,
      "posX": 1617.1944801964785,
      "posY": 2481.194480196478,
      "posZ": 0.0,
      "type": "Unit"
    },
    {
      "id": 84,
      "posX": 1840.3522422943884,
      "posY": 9987.722389554738,
      "posZ": 0.0,
      "type": "Unit"
    },
    {
      "id": 85,
      "posX": 8742.521861300698,
      "posY": 5297.521861300698,
      "posZ": 0.0,
      "type": "Unit"
    },
    {
      "id": 86,
      "posX": 7780.5999999999995,
      "posY": 9792.199999999999,
      "posZ": 0.0,
      "type": "Unit"
    },
    {
      "id": 87,
      "posX": 7345.0,
      "posY": 9967.0,
      "posZ": 0.0,
      "type": "Unit"
    },
    {
      "id": 88,
      "posX": 9504.0,
      "posY": 1235.0,
      "posZ": 0.0,
      "type": "Unit"
    },
    {
      "id": 89,
      "posX": 771.7798653909831,
      "posY": 2511.559730781966,
      "posZ": 0.0,
      "type": "Unit"
    },
    {
      "id": 90,
      "posX": 7495.858608905003,
      "posY": 8948.7879133575,
      "posZ": 0.0,
      "type": "Unit"
    },
    {
      "id": 91,
      "posX": 3272.6479813469905,
      "posY": 2143.29596269398,
      "posZ": 0.0,
      "type": "Unit"
    },
    {
      "id": 92,
      "posX": 3971.0,
      "posY": 9212.0,
      "posZ": 0.0,
      "type": "Unit"
    },
    {
      "id": 93,
      "posX": 6353.798144482504,
      "posY": 4248.7553493869445,
      "posZ": 0.0,
      "type": "Unit"
    },
    {
      "id": 94,
      "posX": 7636.0,
      "posY": 4237.0,
      "posZ": 0.0,
      "type": "Unit"
    },
    {
      "id": 95,
      "posX": 6821.005178374525,
      "posY": 1583.115714110689,
      "posZ": 0.0,
      "type": "Unit"
    },
    {
      "id": 96,
      "posX": 488.51310230148965,
      "posY": 5536.523584142681,
      "posZ": 0.0,
      "type": "Unit"
    },
    {
      "id": 97,
      "posX": 94.04494123154609,
      "posY": 4205.480894216784,
      "posZ": 0.0,
      "type": "Unit"
    },
    {
      "id": 98,
      "posX": 4917.0,
      "posY": 6175.0,
      "posZ": 0.0,
      "type": "Unit"
    },
    {
      "id": 99,
      "posX": 8345.72462985207,
      "posY": 4499.207037100592,
      "posZ": 0.0,
      "type": "Unit"
    },
    {
      "id": 100,
      "posX": 8472.094740162009,
      "posY": 7139.66318113408,
      "posZ": 0.0,
      "type": "Unit"
    },
    {
      "id": 101,
      "posX": 6589.356514161586,
      "posY": 8175.069542484759,
      "posZ": 0.0,
      "type": "Unit"
    },
    {
      "id": 102,
      "posX": 6158.268989535725,
      "posY": 6962.960975583358,
      "posZ": 0.0,
      "type": "Unit"
    },
    {
      "id": 103,
      "posX": 8551.72691505197,
      "posY": 7062.363457525985,
      "posZ": 0.0,
      "type": "Unit"
    },
    {
      "id": 104,
      "posX": 6745.623058987491,
      "posY": 4534.24611797498,
      "posZ": 0.0,
      "type": "Unit"
    },
    {
      "id": 105,
      "posX": 9175.783462251931,
      "posY": 2770.296847152704,
      "posZ": 0.0,
      "type": "Unit"
    },
    {
      "id": 106,
      "posX": 2974.639695279188,
      "posY": 9122.727939055838,
      "posZ": 0.0,
      "type": "Unit"
    },
    {
      "id": 107,
      "posX": 9060.700760239863,
      "posY": 8569.726330419762,
      "posZ": 0.0,
      "type": "Unit"
    },
    {
      "id": 108,
      "posX": 1267.361437646114,
      "posY": 2677.635107226351,
      "posZ": 0.0,
      "type": "Unit"
    },
    {
      "id": 109,
      "posX": 4404.308657865101,
      "posY": 228.30865786510145,
      "posZ": 0.0,
      "type": "Unit"
    },
    {
      "id": 110,
      "posX": 5042.459147565486,
      "posY": 3703.377442696457,
      "posZ": 0.0,
      "type": "Unit"
    },
    {
      "id": 111,
      "posX": 7681.456248271406,
      "posY": 8929.68437240711,
      "posZ": 0.0,
      "type": "Unit"
    },
    {
      "id": 112,
      "posX": 9042.620887067671,
      "posY": 6053.620887067671,
      "posZ": 0.0,
      "type": "Unit"
    },
    {
      "id": 113,
      "posX": 6412.199999999999,
      "posY": 3550.4000000000005,
      "posZ": 0.0,
      "type": "Unit"
    },
    {
      "id": 114,
      "posX": 6361.148382518747,
      "posY": 8598.287095629685,
      "posZ": 0.0,
      "type": "Unit"
    },
    {
      "id": 115,
      "posX": 4668.62560941881,
      "posY": 2423.9384141282167,
      "posZ": 0.0,
      "type": "Unit"
    },
    {
      "id": 116,
      "posX": 1909.8528137423857,
      "posY": 6067.852813742386,
      "posZ": 0.0,
      "type": "Unit"
    },
    {
      "id": 117,
      "posX": 9431.700666324305,
      "posY": 9964.203997945844,
      "posZ": 0.0,
      "type": "Unit"
    },
    {
      "id": 118,
      "posX": 4167.213203435597,
      "posY": 481.2132034355964,
      "posZ": 0.0,
      "type": "Unit"
    },
    {
      "id": 119,
      "posX": 2260.203915431768,
      "posY": 4094.6117462953043,
      "posZ": 0.0,
      "type": "Unit"
    },
    {
      "id": 120,
      "posX": 7654.732139211339,
      "posY": 8188.239283526803,
      "posZ": 0.0,
      "type": "Unit"
    },
    {
      "id": 121,
      "posX": 4350.723660659591,
      "posY": 2336.6891182420395,
      "posZ": 0.0,
      "type": "Unit"
    },
    {
      "id": 122,
      "posX": 8883.768891000338,
      "posY": 8524.84445500169,
      "posZ": 0.0,
      "type": "Unit"
    },
    {
      "id": 123,
      "posX": 4903.095108286991,
      "posY": 4041.277626334822,
      "posZ": 0.0,
      "type": "Unit"
    },
    {
      "id": 124,
      "posX": 1646.3168520523864,
      "posY": 4496.509362251326,
      "posZ": 0.0,
      "type": "Unit"
    },
    {
      "id": 125,
      "posX": 2746.0,
      "posY": 9267.0,
      "posZ": 0.0,
      "type": "Unit"
    },
    {
      "id": 126,
      "posX": 1849.488852711707,
      "posY": 8816.48885271171,
      "posZ": 0.0,
      "type": "Unit"
    },
    {
      "id": 127,
      "posX": 9715.0,
      "posY": 4210.0,
      "posZ": 0.0,
      "type": "Unit"
    },
    {
      "id": 128,
      "posX": 2165.9887381868493,
      "posY": 542.1207768200688,
      "posZ": 0.0,
      "type": "Unit"
    },
    {
      "id": 129,
      "posX": 5338.097246346838,
      "posY": 3630.520080491985,
      "posZ": 0.0,
      "type": "Unit"
    },
    {
      "id": 130,
      "posX": 3375.693814221947,
      "posY": 1642.5168379251925,
      "posZ": 0.0,
      "type": "Unit"
    },
    {
      "id": 131,
      "posX": 4684.8999229583505,
      "posY": 8580.34988443753,
      "posZ": 0.0,
      "type": "Unit"
    },
    {
      "id": 132,
      "posX": 9974.249223594998,
      "posY": 6579.124611797499,
      "posZ": 0.0,
      "type": "Unit"
    },
    {
      "id": 133,
      "posX": 6492.0,
      "posY": 3762.0,
      "posZ": 0.0,
      "type": "Unit"
    },
    {
      "id": 134,
      "posX": 2111.0,
      "posY": 2212.0,
      "posZ": 0.0,
      "type": "Unit"
    },
    {
      "id": 135,
      "posX": 2415.15218613007,
      "posY": 2226.0653029104888,
      "posZ": 0.0,
      "type": "Unit"
    },
    {
      "id": 136,
      "posX": 8480.469661940377,
      "posY": 1466.4831455224307,
      "posZ": 0.0,
      "type": "Unit"
    },
    {
      "id": 137,
      "posX": 742.521344962949,
      "posY": 3157.7340805349713,
      "posZ": 0.0,
      "type": "Unit"
    },
    {
      "id": 138,
      "posX": 7256.459415460184,
      "posY": 3099.4594154601837,
      "posZ": 0.0,
      "type": "Unit"
    },
    {
      "id": 139,
      "posX": 3071.0,
      "posY": 9050.0,
      "posZ": 0.0,
      "type": "Unit"
    },
    {
      "id": 140,
      "posX": 837.1743041809385,
      "posY": 8838.908256020106,
      "posZ": 0.0,
      "type": "Unit"
    },
    {
      "id": 141,
      "posX": 6065.298662650062,
      "posY": 2908.5656265056036,
      "posZ": 0.0,
      "type": "Unit"
    },
    {
      "id": 142,
      "posX": 5690.595504664255,
      "posY": 3273.0719083956565,
      "posZ": 0.0,
      "type": "Unit"
    },
    {
      "id": 143,
      "posX": 71.0,
      "posY": 7780.0,
      "posZ": 0.0,
      "type": "Unit"
    },
    {
      "id": 144,
      "posX": 1893.7312825013082,
      "posY": 311.925130005232,
      "posZ": 0.0,
      "type": "Unit"
    },
    {
      "id": 145,
      "posX": 7484.0,
      "posY": 3593.0,
      "posZ": 0.0,
      "type": "Unit"
    },
    {
      "id": 146,
      "posX": 7445.998648623971,
      "posY": 5330.995945871911,
      "posZ": 0.0,
      "type": "Unit"
    },
    {
      "id": 147,
      "posX": 7516.251913336867,
      "posY": 2782.129783342166,
      "posZ": 0.0,
      "type": "Unit"
    },
    {
      "id": 148,
      "posX": 4160.960665845773,
      "posY": 2734.561775588729,
      "posZ": 0.0,
      "type": "Unit"
    },
    {
      "id": 149,
      "posX": 4478.881889712894,
      "posY": 1573.9015747607439,
      "posZ": 0.0,
      "type": "Unit"
    },
    {
      "id": 150,
      "posX": 6575.0,
      "posY": 1812.0,
      "posZ": 0.0,
      "type": "Unit"
    },
    {
      "id": 151,
      "posX": 3193.826964738928,
      "posY": 6424.681647077181,
      "posZ": 0.0,
      "type": "Unit"
    },
    {
      "id": 152,
      "posX": 2354.2293505688763,
      "posY": 4863.91437228543,
      "posZ": 0.0,
      "type": "Unit"
    },
    {
      "id": 153,
      "posX": 7029.152793129807,
      "posY": 3114.625019738321,
      "posZ": 0.0,
      "type": "Unit"
    },
    {
      "id": 154,
      "posX": 5784.3440203032005,
      "posY": 8757.384005800914,
      "posZ": 0.0,
      "type": "Unit"
    },
    {
      "id": 155,
      "posX": 349.33809511662434,
      "posY": 3235.3380951166237,
      "posZ": 0.0,
      "type": "Unit"
    },
    {
      "id": 156,
      "posX": 6016.36396103068,
      "posY": 9943.36396103068,
      "posZ": 0.0,
      "type": "Unit"
    },
    {
      "id": 157,
      "posX": 7841.0,
      "posY": 4452.0,
      "posZ": 0.0,
      "type": "Unit"
    },
    {
      "id": 158,
      "posX": 8071.981651204021,
      "posY": 3138.331294578225,
      "posZ": 0.0,
      "type": "Unit"
    },
    {
      "id": 159,
      "posX": 8056.904748240735,
      "posY": 6659.555539614193,
      "posZ": 0.0,
      "type": "Unit"
    },
    {
      "id": 160,
      "posX": 2413.0,
      "posY": 7327.0,
      "posZ": 0.0,
      "type": "Unit"
    },
    {
      "id": 161,
      "posX": 8886.10674064953,
      "posY": 8940.617975065414,
      "posZ": 0.0,
      "type": "Unit"
    },
    {
      "id": 162,
      "posX": 1907.6283765582405,
      "posY": 693.9305008904229,
      "posZ": 0.0,
      "type": "Unit"
    },
    {
      "id": 163,
      "posX": 974.9047482407357,
      "posY": 7421.555539614193,
      "posZ": 0.0,
      "type": "Unit"
    },
    {
      "id": 164,
      "posX": 8330.312804709405,
      "posY": 2398.9692070641076,
      "posZ": 0.0,
      "type": "Unit"
    },
    {
      "id": 165,
      "posX": 8824.488452649039,
      "posY": 7378.992301766028,
      "posZ": 0.0,
      "type": "Unit"
    },
    {
      "id": 166,
      "posX": 6814.910427500435,
      "posY": 2375.6417100017443,
      "posZ": 0.0,
      "type": "Unit"
    },
    {
      "id": 167,
      "posX": 4307.744208407536,
      "posY": 8805.953667260284,
      "posZ": 0.0,
      "type": "Unit"
    },
    {
      "id": 168,
      "posX": 9985.807964384108,
      "posY": 943.1299777400667,
      "posZ": 0.0,
      "type": "Unit"
    },
    {
      "id": 169,
      "posX": 6560.232625222607,
      "posY": 1508.8610017808458,
      "posZ": 0.0,
      "type": "Unit"
    },
    {
      "id": 170,
      "posX": 1406.3639610306786,
      "posY": 8006.36396103068,
      "posZ": 0.0,
      "type": "Unit"
    },
    {
      "id": 171,
      "posX": 6704.230249470757,
      "posY": 9708.743416490253,
      "posZ": 0.0,
      "type": "Unit"
    },
    {
      "id": 172,
      "posX": 9781.0,
      "posY": 7610.0,
      "posZ": 0.0,
      "type": "Unit"
    },
    {
      "id": 173,
      "posX": 4029.0,
      "posY": 1894.0,
      "posZ": 0.0,
      "type": "Unit"
    },
    {
      "id": 174,
      "posX": 620.3656412506541,
      "posY": 2084.4625650026164,
      "posZ": 0.0,
      "type": "Unit"
    },
    {
      "id": 175,
      "posX": 8079.055638569974,
      "posY": 3426.2445108559796,
      "posZ": 0.0,
      "type": "Unit"
    },
    {
      "id": 176,
      "posX": 1580.3282011773513,
      "posY": 8055.992301766028,
      "posZ": 0.0,
      "type": "Unit"
    },
    {
      "id": 177,
      "posX": 4183.283420003489,
      "posY": 4759.820855000872,
      "posZ": 0.0,
      "type": "Unit"
    },
    {
      "id": 178,
      "posX": 7450.044937663537,
      "posY": 3763.2668516238264,
      "posZ": 0.0,
      "type": "Unit"
    },
    {
      "id": 179,
      "posX": 5004.727922061357,
      "posY": 9202.72792206136,
      "posZ": 0.0,
      "type": "Unit"
    },
    {
      "id": 180,
      "posX": 7071.606601717797,
      "posY": 16.606601717798213,
      "posZ": 0.0,
      "type": "Unit"
    },
    {
      "id": 181,
      "posX": 6723.059480720433,
      "posY": 1409.4540631659,
      "posZ": 0.0,
      "type": "Unit"
    },
    {
      "id": 182,
      "posX": 8476.685032174375,
      "posY": 1507.7125804359348,
      "posZ": 0.0,
      "type": "Unit"
    },
    {
      "id": 183,
      "posX": 3792.5555396141913,
      "posY": 2767.499928263863,
      "posZ": 0.0,
      "type": "Unit"
    },
    {
      "id": 184,
      "posX": 6792.0,
      "posY": 1359.0,
      "posZ": 0.0,
      "type": "Unit"
    },
    {
      "id": 185,
      "posX": 4618.149534156998,
      "posY": 3740.074767078499,
      "posZ": 0.0,
      "type": "Unit"
    },
    {
      "id": 186,
      "posX": 6796.099689438,
      "posY": 5918.049844718998,
      "posZ": 0.0,
      "type": "Unit"
    },
    {
      "id": 187,
      "posX": 5310.370786380607,
      "posY": 2997.867415485094,
      "posZ": 0.0,
      "type": "Unit"
    },
    {
      "id": 188,
      "posX": 8907.600000000002,
      "posY": 3413.2000000000003,
      "posZ": 0.0,
      "type": "Unit"
    },
    {
      "id": 189,
      "posX": 4359.090547374425,
      "posY": 7138.544610540324,
      "posZ": 0.0,
      "type": "Unit"
    },
    {
      "id": 190,
      "posX": 8272.0,
      "posY": 5357.0,
      "posZ": 0.0,
      "type": "Unit"
    },
    {
      "id": 191,
      "posX": 6491.64870412073,
      "posY": 4085.473056181095,
      "posZ": 0.0,
      "type": "Unit"
    },
    {
      "id": 192,
      "posX": 1230.9444532170317,
      "posY": 578.7345747243583,
      "posZ": 0.0,
      "type": "Unit"
    },
    {
      "id": 193,
      "posX": 9275.055638569977,
      "posY": 2817.2445108559796,
      "posZ": 0.0,
      "type": "Unit"
    },
    {
      "id": 194,
      "posX": 9342.498010508592,
      "posY": 6157.7992042034375,
      "posZ": 0.0,
      "type": "Unit"
    },
    {
      "id": 195,
      "posX": 3824.6920997883035,
      "posY": 3464.8973665961016,
      "posZ": 0.0,
      "type": "Unit"
    },
    {
      "id": 196,
      "posX": 524.6934312304156,
      "posY": 9038.97080372258,
      "posZ": 0.0,
      "type": "Unit"
    },
    {
      "id": 197,
      "posX": 3635.499928263863,
      "posY": 5390.555539614193,
      "posZ": 0.0,
      "type": "Unit"
    },
    {
      "id": 198,
      "posX": 588.8841681507049,
      "posY": 9350.860521018836,
      "posZ": 0.0,
      "type": "Unit"
    },
    {
      "id": 199,
      "posX": 4898.800000000001,
      "posY": 7954.5999999999995,
      "posZ": 0.0,
      "type": "Unit"
    },
    {
      "id": 200,
      "posX": 7239.76187060184,
      "posY": 2773.388849035479,
      "posZ": 0.0,
      "type": "Unit"
    },
    {
      "id": 201,
      "posX": 8127.631984736046,
      "posY": 130.76999046002862,
      "posZ": 0.0,
      "type": "Unit"
    },
    {
      "id": 202,
      "posX": 7141.230249470757,
      "posY": 8483.743416490253,
      "posZ": 0.0,
      "type": "Unit"
    },
    {
      "id": 203,
      "posX": 9234.0,
      "posY": 7064.0,
      "posZ": 0.0,
      "type": "Unit"
    },
    {
      "id": 204,
      "posX": 8886.0,
      "posY": 5560.0,
      "posZ": 0.0,
      "type": "Unit"
    },
    {
      "id": 205,
      "posX": 2700.6380343755454,
      "posY": 9369.552137502182,
      "posZ": 0.0,
      "type": "Unit"
    },
    {
      "id": 206,
      "posX": 4577.12132034356,
      "posY": 5720.12132034356,
      "posZ": 0.0,
      "type": "Unit"
    },
    {
      "id": 207,
      "posX": 8693.969848480985,
      "posY": 8582.42426406871,
      "posZ": 0.0,
      "type": "Unit"
    },
    {
      "id": 208,
      "posX": 4810.6564728911235,
      "posY": 7010.908256020103,
      "posZ": 0.0,
      "type": "Unit"
    },
    {
      "id": 209,
      "posX": 4230.0,
      "posY": 6956.0,
      "posZ": 0.0,
      "type": "Unit"
    },
    {
      "id": 210,
      "posX": 9167.984603532055,
      "posY": 6162.656402354703,
      "posZ": 0.0,
      "type": "Unit"
    },
    {
      "id": 211,
      "posX": 4390.889907224124,
      "posY": 9884.987767469347,
      "posZ": 0.0,
      "type": "Unit"
    },
    {
      "id": 212,
      "posX": 4158.384199576607,
      "posY": 4029.794733192202,
      "posZ": 0.0,
      "type": "Unit"
    },
    {
      "id": 213,
      "posX": 3615.0,
      "posY": 9992.0,
      "posZ": 0.0,
      "type": "Unit"
    },
    {
      "id": 214,
      "posX": 3696.0,
      "posY": 7756.0,
      "posZ": 0.0,
      "type": "Unit"
    },
    {
      "id": 215,
      "posX": 4557.0,
      "posY": 9945.0,
      "posZ": 0.0,
      "type": "Unit"
    },
    {
      "id": 216,
      "posX": 4754.0,
      "posY": 7044.0,
      "posZ": 0.0,
      "type": "Unit"
    },
    {
      "id": 217,
      "posX": 4195.0,
      "posY": 4838.0,
      "posZ": 0.0,
      "type": "Unit"
    },
    {
      "id": 218,
      "posX": 8146.0,
      "posY": 9751.0,
      "posZ": 0.0,
      "type": "Unit"
    },
    {
      "id": 219,
      "posX": 323.0,
      "posY": 4762.0,
      "posZ": 0.0,
      "type": "Unit"
    },
    {
      "id": 220,
      "posX": 8487.0,
      "posY": 1745.0,
      "posZ": 0.0,
      "type": "Unit"
    },
    {
      "id": 221,
      "posX": 7255.0,
      "posY": 6479.0,
      "posZ": 0.0,
      "type": "Unit"
    },
    {
      "id": 222,
      "posX": 5145.0,
      "posY": 1071.0,
      "posZ": 0.0,
      "type": "Unit"
    },
    {
      "id": 223,
      "posX": 955.0,
      "posY": 1159.0,
      "posZ": 0.0,
      "type": "Unit"
    },
    {
      "id": 224,
      "posX": 7760.0,
      "posY": 5870.0,
      "posZ": 0.0,
      "type": "Unit"
    },
    {
      "id": 225,
      "posX": 2056.0,
      "posY": 5736.0,
      "posZ": 0.0,
      "type": "Unit"
    },
    {
      "id": 226,
      "posX": 9884.0,
      "posY": 8138.0,
      "posZ": 0.0,
      "type": "Unit"
    },
    {
      "id": 227,
      "posX": 9523.0,
      "posY": 2817.0,
      "posZ": 0.0,
      "type": "Unit"
    },
    {
      "id": 228,
      "posX": 9162.0,
      "posY": 8948.0,
      "posZ": 0.0,
      "type": "Unit"
    },
    {
      "id": 229,
      "posX": 3056.0,
      "posY": 9491.0,
      "posZ": 0.0,
      "type": "Unit"
    },
    {
      "id": 230,
      "posX": 5788.0,
      "posY": 9210.0,
      "posZ": 0.0,
      "type": "Unit"
    },
    {
      "id": 231,
      "posX": 6254.0,
      "posY": 3966.0,
      "posZ": 0.0,
      "type": "Unit"
    },
    {
      "id": 232,
      "posX": 5156.0,
      "posY": 6894.0,
      "posZ": 0.0,
      "type": "Unit"
    },
    {
      "id": 233,
      "posX": 6645.0,
      "posY": 6802.0,
      "posZ": 0.0,
      "type": "Unit"
    },
    {
      "id": 234,
      "posX": 1564.0,
      "posY": 3303.0,
      "posZ": 0.0,
      "type": "Unit"
    },
    {
      "id": 235,
      "posX": 5048.0,
      "posY": 6969.0,
      "posZ": 0.0,
      "type": "Unit"
    },
    {
      "id": 236,
      "posX": 9800.0,
      "posY": 6404.0,
      "posZ": 0.0,
      "type": "Unit"
    },
    {
      "id": 237,
      "posX": 7475.0,
      "posY": 8655.0,
      "posZ": 0.0,
      "type": "Unit"
    },
    {
      "id": 238,
      "posX": 9815.0,
      "posY": 4946.0,
      "posZ": 0.0,
      "type": "Unit"
    },
    {
      "id": 239,
      "posX": 816.0,
      "posY": 4782.0,
      "posZ": 0.0,
      "type": "Unit"
    },
    {
      "id": 240,
      "posX": 6871.0,
      "posY": 3927.0,
      "posZ": 0.0,
      "type": "Unit"
    },
    {
      "id": 241,
      "posX": 8418.0,
      "posY": 9225.0,
      "posZ": 0.0,
      "type": "Unit"
    },
    {
      "id": 242,
      "posX": 2042.0,
      "posY": 3107.0,
      "posZ": 0.0,
      "type": "Unit"
    },
    {
      "id": 243,
      "posX": 8407.0,
      "posY": 4293.0,
      "posZ": 0.0,
      "type": "Unit"
    },
    {
      "id": 244,
      "posX": 3784.0,
      "posY": 7556.0,
      "posZ": 0.0,
      "type": "Unit"
    },
    {
      "id": 245,
      "posX": 6766.0,
      "posY": 1464.0,
      "posZ": 0.0,
      "type": "Unit"
    },
    {
      "id": 246,
      "posX": 5430.0,
      "posY": 9572.0,
      "posZ": 0.0,
      "type": "Unit"
    },
    {
      "id": 247,
      "posX": 2818.0,
      "posY": 9373.0,
      "posZ": 0.0,
      "type": "Unit"
    },
    {
      "id": 248,
      "posX": 2527.0,
      "posY": 6938.0,
      "posZ": 0.0,
      "type": "Unit"
    },
    {
      "id": 249,
      "posX": 241.0,
      "posY": 9464.0,
      "posZ": 0.0,
      "type": "Unit"
    },
    {
      "id": 250,
      "posX": 2785.0,
      "posY": 443.0,
      "posZ": 0.0,
      "type": "Unit"
    },
    {
      "id": 251,
      "posX": 6847.0,
      "posY": 1641.0,
      "posZ": 0.0,
      "type": "Unit"
    },
    {
      "id": 252,
      "posX": 297.0,
      "posY": 2585.0,
      "posZ": 0.0,
      "type": "Unit"
    },
    {
      "id": 253,
      "posX": 3883.0,
      "posY": 675.0,
      "posZ": 0.0,
      "type": "Unit"
    },
    {
      "id": 254,
      "posX": 1809.0,
      "posY": 6464.0,
      "posZ": 0.0,
      "type": "Unit"
    },
    {
      "id": 255,
      "posX": 391.0,
      "posY": 1052.0,
      "posZ": 0.0,
      "type": "Unit"
    },
    {
      "id": 256,
      "posX": 277.0,
      "posY": 8680.0,
      "posZ": 0.0,
      "type": "Unit"
    },
    {
      "id": 257,
      "posX": 8139.0,
      "posY": 5161.0,
      "posZ": 0.0,
      "type": "Unit"
    },
    {
      "id": 258,
      "posX": 9455.0,
      "posY": 8671.0,
      "posZ": 0.0,
      "type": "Unit"
    },
    {
      "id": 259,
      "posX": 2580.0,
      "posY": 6547.0,
      "posZ": 0.0,
      "type": "Unit"
    },
    {
      "id": 260,
      "posX": 8011.0,
      "posY": 9591.0,
      "posZ": 0.0,
      "type": "Unit"
    },
    {
      "id": 261,
      "posX": 9164.0,
      "posY": 9346.0,
      "posZ": 0.0,
      "type": "Unit"
    },
    {
      "id": 262,
      "posX": 5071.0,
      "posY": 9793.0,
      "posZ": 0.0,
      "type": "Unit"
    },
    {
      "id": 263,
      "posX": 6731.0,
      "posY": 8334.0,
      "posZ": 0.0,
      "type": "Unit"
    },
    {
      "id": 264,
      "posX": 7798.0,
      "posY": 3950.0,
      "posZ": 0.0,
      "type": "Unit"
    },
    {
      "id": 265,
      "posX": 4394.0,
      "posY": 6973.0,
      "posZ": 0.0,
      "type": "Unit"
    },
    {
      "id": 266,
      "posX": 4966.0,
      "posY": 6935.0,
      "posZ": 0.0,
      "type": "Unit"
    },
    {
      "id": 267,
      "posX": 5873.0,
      "posY": 7593.0,
      "posZ": 0.0,
      "type": "Unit"
    },
    {
      "id": 268,
      "posX": 4620.0,
      "posY": 1615.0,
      "posZ": 0.0,
      "type": "Unit"
    },
    {
      "id": 269,
      "posX": 8079.0,
      "posY": 6108.0,
      "posZ": 0.0,
      "type": "Unit"
    },
    {
      "id": 270,
      "posX": 3512.0,
      "posY": 6430.0,
      "posZ": 0.0,
      "type": "Unit"
    },
    {
      "id": 271,
      "posX": 1462.0,
      "posY": 4823.0,
      "posZ": 0.0,
      "type": "Unit"
    },
    {
      "id": 272,
      "posX": 9984.0,
      "posY": 141.0,
      "posZ": 0.0,
      "type": "Unit"
    },
    {
      "id": 273,
      "posX": 8813.0,
      "posY": 9602.0,
      "posZ": 0.0,
      "type": "Unit"
    },
    {
      "id": 274,
      "posX": 2501.0,
      "posY": 5791.0,
      "posZ": 0.0,
      "type": "Unit"
    },
    {
      "id": 275,
      "posX": 5383.0,
      "posY": 1393.0,
      "posZ": 0.0,
      "type": "Unit"
    },
    {
      "id": 276,
      "posX": 7091.0,
      "posY": 512.0,
      "posZ": 0.0,
      "type": "Unit"
    },
    {
      "id": 277,
      "posX": 305.0,
      "posY": 899.0,
      "posZ": 0.0,
      "type": "Unit"
    },
    {
      "id": 278,
      "posX": 9233.0,
      "posY": 8515.0,
      "posZ": 0.0,
      "type": "Unit"
    },
    {
      "id": 279,
      "posX": 8817.0,
      "posY": 3388.0,
      "posZ": 0.0,
      "type": "Unit"
    },
    {
      "id": 280,
      "posX": 6713.0,
      "posY": 3384.0,
      "posZ": 0.0,
      "type": "Unit"
    },
    {
      "id": 281,
      "posX": 319.0,
      "posY": 3211.0,
      "posZ": 0.0,
      "type": "Unit"
    },
    {
      "id": 282,
      "posX": 7157.0,
      "posY": 1680.0,
      "posZ": 0.0,
      "type": "Unit"
    },
    {
      "id": 283,
      "posX": 3295.0,
      "posY": 2544.0,
      "posZ": 0.0,
      "type": "Unit"
    },
    {
      "id": 284,
      "posX": 8653.0,
      "posY": 1777.0,
      "posZ": 0.0,
      "type": "Unit"
    },
    {
      "id": 285,
      "posX": 8207.0,
      "posY": 7727.0,
      "posZ": 0.0,
      "type": "Unit"
    },
    {
      "id": 286,
      "posX": 2550.0,
      "posY": 8517.0,
      "posZ": 0.0,
      "type": "Unit"
    },
    {
      "id": 287,
      "posX": 8659.0,
      "posY": 6022.0,
      "posZ": 0.0,
      "type": "Unit"
    },
    {
      "id": 288,
      "posX": 1976.0,
      "posY": 8886.0,
      "posZ": 0.0,
      "type": "Unit"
    },
    {
      "id": 289,
      "posX": 4678.0,
      "posY": 3824.0,
      "posZ": 0.0,
      "type": "Unit"
    },
    {
      "id": 290,
      "posX": 1569.0,
      "posY": 4477.0,
      "posZ": 0.0,
      "type": "Unit"
    },
    {
      "id": 291,
      "posX": 1341.0,
      "posY": 6413.0,
      "posZ": 0.0,
      "type": "Unit"
    },
    {
      "id": 292,
      "posX": 7312.0,
      "posY": 5012.0,
      "posZ": 0.0,
      "type": "Unit"
    },
    {
      "id": 293,
      "posX": 3527.0,
      "posY": 7998.0,
      "posZ": 0.0,
      "type": "Unit"
    },
    {
      "id": 294,
      "posX": 1386.0,
      "posY": 6545.0,
      "posZ": 0.0,
      "type": "Unit"
    },
    {
      "id": 295,
      "posX": 6281.0,
      "posY": 2345.0,
      "posZ": 0.0,
      "type": "Unit"
    },
    {
      "id": 296,
      "posX": 1908.0,
      "posY": 8100.0,
      "posZ": 0.0,
      "type": "Unit"
    },
    {
      "id": 297,
      "posX": 6132.0,
      "posY": 2953.0,
      "posZ": 0.0,
      "type": "Unit"
    }
  ],
  "relation": [
    {
      "entity1": 0,
      "entity2": 101
    },
    {
      "entity1": 0,
      "entity2": 114
    },
    {
      "entity1": 0,
      "entity2": 263
    },
    {
      "entity1": 1,
      "entity2": 29
    },
    {
      "entity1": 2,
      "entity2": 124
    },
    {
      "entity1": 2,
      "entity2": 290
    },
    {
      "entity1": 2,
      "entity2": 271
    },
    {
      "entity1": 3,
      "entity2": 38
    },
    {
      "entity1": 3,
      "entity2": 68
    },
    {
      "entity1": 3,
      "entity2": 261
    },
    {
      "entity1": 4,
      "entity2": 80
    },
    {
      "entity1": 5,
      "entity2": 12
    },
    {
      "entity1": 5,
      "entity2": 69
    },
    {
      "entity1": 5,
      "entity2": 286
    },
    {
      "entity1": 5,
      "entity2": 16
    },
    {
      "entity1": 6,
      "entity2": 56
    },
    {
      "entity1": 6,
      "entity2": 37
    },
    {
      "entity1": 6,
      "entity2": 25
    },
    {
      "entity1": 6,
      "entity2": 290
    },
    {
      "entity1": 6,
      "entity2": 271
    },
    {
      "entity1": 6,
      "entity2": 239
    },
    {
      "entity1": 6,
      "entity2": 124
    },
    {
      "entity1": 7,
      "entity2": 101
    },
    {
      "entity1": 7,
      "entity2": 267
    },
    {
      "entity1": 8,
      "entity2": 111
    },
    {
      "entity1": 8,
      "entity2": 86
    },
    {
      "entity1": 8,
      "entity2": 260
    },
    {
      "entity1": 8,
      "entity2": 218
    },
    {
      "entity1": 9,
      "entity2": 54
    },
    {
      "entity1": 9,
      "entity2": 67
    },
    {
      "entity1": 9,
      "entity2": 201
    },
    {
      "entity1": 10,
      "entity2": 55
    },
    {
      "entity1": 10,
      "entity2": 276
    },
    {
      "entity1": 10,
      "entity2": 54
    },
    {
      "entity1": 11,
      "entity2": 256
    },
    {
      "entity1": 11,
      "entity2": 140
    },
    {
      "entity1": 12,
      "entity2": 286
    },
    {
      "entity1": 12,
      "entity2": 5
    },
    {
      "entity1": 13,
      "entity2": 48
    },
    {
      "entity1": 13,
      "entity2": 36
    },
    {
      "entity1": 13,
      "entity2": 136
    },
    {
      "entity1": 13,
      "entity2": 182
    },
    {
      "entity1": 13,
      "entity2": 220
    },
    {
      "entity1": 13,
      "entity2": 284
    },
    {
      "entity1": 15,
      "entity2": 50
    },
    {
      "entity1": 15,
      "entity2": 102
    },
    {
      "entity1": 16,
      "entity2": 69
    },
    {
      "entity1": 16,
      "entity2": 5
    },
    {
      "entity1": 17,
      "entity2": 44
    },
    {
      "entity1": 18,
      "entity2": 87
    },
    {
      "entity1": 18,
      "entity2": 171
    },
    {
      "entity1": 19,
      "entity2": 225
    },
    {
      "entity1": 19,
      "entity2": 43
    },
    {
      "entity1": 19,
      "entity2": 116
    },
    {
      "entity1": 20,
      "entity2": 161
    },
    {
      "entity1": 20,
      "entity2": 228
    },
    {
      "entity1": 20,
      "entity2": 207
    },
    {
      "entity1": 20,
      "entity2": 122
    },
    {
      "entity1": 20,
      "entity2": 107
    },
    {
      "entity1": 20,
      "entity2": 261
    },
    {
      "entity1": 20,
      "entity2": 68
    },
    {
      "entity1": 21,
      "entity2": 291
    },
    {
      "entity1": 21,
      "entity2": 294
    },
    {
      "entity1": 22,
      "entity2": 75
    },
    {
      "entity1": 22,
      "entity2": 224
    },
    {
      "entity1": 22,
      "entity2": 257
    },
    {
      "entity1": 22,
      "entity2": 190
    },
    {
      "entity1": 23,
      "entity2": 53
    },
    {
      "entity1": 23,
      "entity2": 71
    },
    {
      "entity1": 24,
      "entity2": 58
    },
    {
      "entity1": 25,
      "entity2": 56
    },
    {
      "entity1": 25,
      "entity2": 37
    },
    {
      "entity1": 25,
      "entity2": 6
    },
    {
      "entity1": 25,
      "entity2": 271
    },
    {
      "entity1": 25,
      "entity2": 290
    },
    {
      "entity1": 25,
      "entity2": 124
    },
    {
      "entity1": 26,
      "entity2": 102
    },
    {
      "entity1": 26,
      "entity2": 233
    },
    {
      "entity1": 26,
      "entity2": 33
    },
    {
      "entity1": 27,
      "entity2": 135
    },
    {
      "entity1": 27,
      "entity2": 134
    },
    {
      "entity1": 28,
      "entity2": 143
    },
    {
      "entity1": 29,
      "entity2": 206
    },
    {
      "entity1": 29,
      "entity2": 1
    },
    {
      "entity1": 30,
      "entity2": 42
    },
    {
      "entity1": 31,
      "entity2": 203
    },
    {
      "entity1": 31,
      "entity2": 165
    },
    {
      "entity1": 32,
      "entity2": 130
    },
    {
      "entity1": 33,
      "entity2": 26
    },
    {
      "entity1": 33,
      "entity2": 186
    },
    {
      "entity1": 33,
      "entity2": 233
    },
    {
      "entity1": 34,
      "entity2": 185
    },
    {
      "entity1": 34,
      "entity2": 289
    },
    {
      "entity1": 34,
      "entity2": 212
    },
    {
      "entity1": 35,
      "entity2": 131
    },
    {
      "entity1": 35,
      "entity2": 167
    },
    {
      "entity1": 36,
      "entity2": 48
    },
    {
      "entity1": 36,
      "entity2": 136
    },
    {
      "entity1": 36,
      "entity2": 182
    },
    {
      "entity1": 36,
      "entity2": 220
    },
    {
      "entity1": 36,
      "entity2": 13
    },
    {
      "entity1": 36,
      "entity2": 284
    },
    {
      "entity1": 37,
      "entity2": 49
    },
    {
      "entity1": 37,
      "entity2": 56
    },
    {
      "entity1": 37,
      "entity2": 25
    },
    {
      "entity1": 37,
      "entity2": 239
    },
    {
      "entity1": 37,
      "entity2": 6
    },
    {
      "entity1": 37,
      "entity2": 271
    },
    {
      "entity1": 38,
      "entity2": 273
    },
    {
      "entity1": 38,
      "entity2": 261
    },
    {
      "entity1": 38,
      "entity2": 68
    },
    {
      "entity1": 38,
      "entity2": 3
    },
    {
      "entity1": 39,
      "entity2": 70
    },
    {
      "entity1": 39,
      "entity2": 242
    },
    {
      "entity1": 39,
      "entity2": 234
    },
    {
      "entity1": 40,
      "entity2": 58
    },
    {
      "entity1": 40,
      "entity2": 290
    },
    {
      "entity1": 40,
      "entity2": 124
    },
    {
      "entity1": 42,
      "entity2": 30
    },
    {
      "entity1": 42,
      "entity2": 238
    },
    {
      "entity1": 43,
      "entity2": 51
    },
    {
      "entity1": 43,
      "entity2": 19
    },
    {
      "entity1": 43,
      "entity2": 116
    },
    {
      "entity1": 43,
      "entity2": 254
    },
    {
      "entity1": 43,
      "entity2": 225
    },
    {
      "entity1": 44,
      "entity2": 17
    },
    {
      "entity1": 44,
      "entity2": 88
    },
    {
      "entity1": 45,
      "entity2": 177
    },
    {
      "entity1": 45,
      "entity2": 217
    },
    {
      "entity1": 46,
      "entity2": 223
    },
    {
      "entity1": 47,
      "entity2": 166
    },
    {
      "entity1": 47,
      "entity2": 200
    },
    {
      "entity1": 48,
      "entity2": 36
    },
    {
      "entity1": 48,
      "entity2": 136
    },
    {
      "entity1": 48,
      "entity2": 182
    },
    {
      "entity1": 48,
      "entity2": 13
    },
    {
      "entity1": 49,
      "entity2": 239
    },
    {
      "entity1": 49,
      "entity2": 56
    },
    {
      "entity1": 49,
      "entity2": 219
    },
    {
      "entity1": 49,
      "entity2": 37
    },
    {
      "entity1": 50,
      "entity2": 15
    },
    {
      "entity1": 50,
      "entity2": 102
    },
    {
      "entity1": 51,
      "entity2": 43
    },
    {
      "entity1": 51,
      "entity2": 116
    },
    {
      "entity1": 51,
      "entity2": 254
    },
    {
      "entity1": 51,
      "entity2": 291
    },
    {
      "entity1": 51,
      "entity2": 294
    },
    {
      "entity1": 52,
      "entity2": 187
    },
    {
      "entity1": 52,
      "entity2": 76
    },
    {
      "entity1": 52,
      "entity2": 142
    },
    {
      "entity1": 53,
      "entity2": 90
    },
    {
      "entity1": 53,
      "entity2": 237
    },
    {
      "entity1": 53,
      "entity2": 120
    },
    {
      "entity1": 53,
      "entity2": 111
    },
    {
      "entity1": 53,
      "entity2": 23
    },
    {
      "entity1": 54,
      "entity2": 55
    },
    {
      "entity1": 54,
      "entity2": 10
    },
    {
      "entity1": 54,
      "entity2": 9
    },
    {
      "entity1": 54,
      "entity2": 67
    },
    {
      "entity1": 55,
      "entity2": 276
    },
    {
      "entity1": 55,
      "entity2": 10
    },
    {
      "entity1": 55,
      "entity2": 54
    },
    {
      "entity1": 56,
      "entity2": 49
    },
    {
      "entity1": 56,
      "entity2": 239
    },
    {
      "entity1": 56,
      "entity2": 37
    },
    {
      "entity1": 56,
      "entity2": 6
    },
    {
      "entity1": 56,
      "entity2": 25
    },
    {
      "entity1": 57,
      "entity2": 119
    },
    {
      "entity1": 58,
      "entity2": 24
    },
    {
      "entity1": 58,
      "entity2": 40
    },
    {
      "entity1": 59,
      "entity2": 62
    },
    {
      "entity1": 59,
      "entity2": 109
    },
    {
      "entity1": 59,
      "entity2": 61
    },
    {
      "entity1": 59,
      "entity2": 118
    },
    {
      "entity1": 60,
      "entity2": 295
    },
    {
      "entity1": 60,
      "entity2": 141
    },
    {
      "entity1": 60,
      "entity2": 297
    },
    {
      "entity1": 61,
      "entity2": 62
    },
    {
      "entity1": 61,
      "entity2": 109
    },
    {
      "entity1": 61,
      "entity2": 59
    },
    {
      "entity1": 62,
      "entity2": 118
    },
    {
      "entity1": 62,
      "entity2": 109
    },
    {
      "entity1": 62,
      "entity2": 59
    },
    {
      "entity1": 62,
      "entity2": 61
    },
    {
      "entity1": 63,
      "entity2": 64
    },
    {
      "entity1": 63,
      "entity2": 179
    },
    {
      "entity1": 64,
      "entity2": 79
    },
    {
      "entity1": 64,
      "entity2": 63
    },
    {
      "entity1": 64,
      "entity2": 179
    },
    {
      "entity1": 66,
      "entity2": 230
    },
    {
      "entity1": 67,
      "entity2": 54
    },
    {
      "entity1": 67,
      "entity2": 9
    },
    {
      "entity1": 68,
      "entity2": 20
    },
    {
      "entity1": 68,
      "entity2": 38
    },
    {
      "entity1": 68,
      "entity2": 228
    },
    {
      "entity1": 68,
      "entity2": 261
    },
    {
      "entity1": 68,
      "entity2": 161
    },
    {
      "entity1": 68,
      "entity2": 3
    },
    {
      "entity1": 69,
      "entity2": 16
    },
    {
      "entity1": 69,
      "entity2": 5
    },
    {
      "entity1": 70,
      "entity2": 39
    },
    {
      "entity1": 70,
      "entity2": 234
    },
    {
      "entity1": 70,
      "entity2": 242
    },
    {
      "entity1": 71,
      "entity2": 23
    },
    {
      "entity1": 71,
      "entity2": 207
    },
    {
      "entity1": 72,
      "entity2": 154
    },
    {
      "entity1": 72,
      "entity2": 230
    },
    {
      "entity1": 72,
      "entity2": 114
    },
    {
      "entity1": 73,
      "entity2": 192
    },
    {
      "entity1": 74,
      "entity2": 236
    },
    {
      "entity1": 74,
      "entity2": 132
    },
    {
      "entity1": 75,
      "entity2": 22
    },
    {
      "entity1": 75,
      "entity2": 257
    },
    {
      "entity1": 75,
      "entity2": 190
    },
    {
      "entity1": 76,
      "entity2": 52
    },
    {
      "entity1": 76,
      "entity2": 141
    },
    {
      "entity1": 77,
      "entity2": 149
    },
    {
      "entity1": 77,
      "entity2": 268
    },
    {
      "entity1": 77,
      "entity2": 222
    },
    {
      "entity1": 78,
      "entity2": 110
    },
    {
      "entity1": 78,
      "entity2": 129
    },
    {
      "entity1": 79,
      "entity2": 92
    },
    {
      "entity1": 79,
      "entity2": 211
    },
    {
      "entity1": 79,
      "entity2": 64
    },
    {
      "entity1": 80,
      "entity2": 4
    },
    {
      "entity1": 80,
      "entity2": 227
    },
    {
      "entity1": 81,
      "entity2": 253
    },
    {
      "entity1": 81,
      "entity2": 118
    },
    {
      "entity1": 83,
      "entity2": 108
    },
    {
      "entity1": 85,
      "entity2": 204
    },
    {
      "entity1": 85,
      "entity2": 190
    },
    {
      "entity1": 86,
      "entity2": 87
    },
    {
      "entity1": 86,
      "entity2": 8
    },
    {
      "entity1": 86,
      "entity2": 260
    },
    {
      "entity1": 86,
      "entity2": 218
    },
    {
      "entity1": 87,
      "entity2": 18
    },
    {
      "entity1": 87,
      "entity2": 86
    },
    {
      "entity1": 88,
      "entity2": 44
    },
    {
      "entity1": 89,
      "entity2": 252
    },
    {
      "entity1": 89,
      "entity2": 174
    },
    {
      "entity1": 90,
      "entity2": 237
    },
    {
      "entity1": 90,
      "entity2": 111
    },
    {
      "entity1": 90,
      "entity2": 53
    },
    {
      "entity1": 91,
      "entity2": 283
    },
    {
      "entity1": 92,
      "entity2": 79
    },
    {
      "entity1": 93,
      "entity2": 191
    },
    {
      "entity1": 93,
      "entity2": 231
    },
    {
      "entity1": 93,
      "entity2": 104
    },
    {
      "entity1": 94,
      "entity2": 157
    },
    {
      "entity1": 94,
      "entity2": 264
    },
    {
      "entity1": 95,
      "entity2": 184
    },
    {
      "entity1": 95,
      "entity2": 181
    },
    {
      "entity1": 95,
      "entity2": 245
    },
    {
      "entity1": 95,
      "entity2": 251
    },
    {
      "entity1": 95,
      "entity2": 282
    },
    {
      "entity1": 95,
      "entity2": 169
    },
    {
      "entity1": 95,
      "entity2": 150
    },
    {
      "entity1": 99,
      "entity2": 243
    },
    {
      "entity1": 100,
      "entity2": 103
    },
    {
      "entity1": 100,
      "entity2": 165
    },
    {
      "entity1": 101,
      "entity2": 7
    },
    {
      "entity1": 101,
      "entity2": 0
    },
    {
      "entity1": 101,
      "entity2": 263
    },
    {
      "entity1": 101,
      "entity2": 114
    },
    {
      "entity1": 102,
      "entity2": 15
    },
    {
      "entity1": 102,
      "entity2": 50
    },
    {
      "entity1": 102,
      "entity2": 26
    },
    {
      "entity1": 103,
      "entity2": 100
    },
    {
      "entity1": 103,
      "entity2": 165
    },
    {
      "entity1": 104,
      "entity2": 93
    },
    {
      "entity1": 105,
      "entity2": 193
    },
    {
      "entity1": 105,
      "entity2": 227
    },
    {
      "entity1": 106,
      "entity2": 125
    },
    {
      "entity1": 106,
      "entity2": 205
    },
    {
      "entity1": 106,
      "entity2": 247
    },
    {
      "entity1": 106,
      "entity2": 139
    },
    {
      "entity1": 106,
      "entity2": 229
    },
    {
      "entity1": 107,
      "entity2": 20
    },
    {
      "entity1": 107,
      "entity2": 122
    },
    {
      "entity1": 107,
      "entity2": 278
    },
    {
      "entity1": 107,
      "entity2": 207
    },
    {
      "entity1": 107,
      "entity2": 161
    },
    {
      "entity1": 107,
      "entity2": 228
    },
    {
      "entity1": 107,
      "entity2": 258
    },
    {
      "entity1": 108,
      "entity2": 83
    },
    {
      "entity1": 109,
      "entity2": 62
    },
    {
      "entity1": 109,
      "entity2": 59
    },
    {
      "entity1": 109,
      "entity2": 61
    },
    {
      "entity1": 109,
      "entity2": 118
    },
    {
      "entity1": 110,
      "entity2": 129
    },
    {
      "entity1": 110,
      "entity2": 185
    },
    {
      "entity1": 110,
      "entity2": 289
    },
    {
      "entity1": 110,
      "entity2": 123
    },
    {
      "entity1": 110,
      "entity2": 78
    },
    {
      "entity1": 111,
      "entity2": 90
    },
    {
      "entity1": 111,
      "entity2": 53
    },
    {
      "entity1": 111,
      "entity2": 237
    },
    {
      "entity1": 111,
      "entity2": 8
    },
    {
      "entity1": 112,
      "entity2": 210
    },
    {
      "entity1": 112,
      "entity2": 194
    },
    {
      "entity1": 112,
      "entity2": 287
    },
    {
      "entity1": 113,
      "entity2": 133
    },
    {
      "entity1": 113,
      "entity2": 280
    },
    {
      "entity1": 113,
      "entity2": 231
    },
    {
      "entity1": 114,
      "entity2": 263
    },
    {
      "entity1": 114,
      "entity2": 72
    },
    {
      "entity1": 114,
      "entity2": 101
    },
    {
      "entity1": 114,
      "entity2": 0
    },
    {
      "entity1": 115,
      "entity2": 121
    },
    {
      "entity1": 116,
      "entity2": 254
    },
    {
      "entity1": 116,
      "entity2": 225
    },
    {
      "entity1": 116,
      "entity2": 51
    },
    {
      "entity1": 116,
      "entity2": 19
    },
    {
      "entity1": 116,
      "entity2": 43
    },
    {
      "entity1": 118,
      "entity2": 253
    },
    {
      "entity1": 118,
      "entity2": 81
    },
    {
      "entity1": 118,
      "entity2": 62
    },
    {
      "entity1": 118,
      "entity2": 109
    },
    {
      "entity1": 118,
      "entity2": 59
    },
    {
      "entity1": 119,
      "entity2": 57
    },
    {
      "entity1": 120,
      "entity2": 53
    },
    {
      "entity1": 121,
      "entity2": 148
    },
    {
      "entity1": 121,
      "entity2": 115
    },
    {
      "entity1": 122,
      "entity2": 207
    },
    {
      "entity1": 122,
      "entity2": 161
    },
    {
      "entity1": 122,
      "entity2": 278
    },
    {
      "entity1": 122,
      "entity2": 20
    },
    {
      "entity1": 122,
      "entity2": 107
    },
    {
      "entity1": 123,
      "entity2": 289
    },
    {
      "entity1": 123,
      "entity2": 185
    },
    {
      "entity1": 123,
      "entity2": 110
    },
    {
      "entity1": 124,
      "entity2": 290
    },
    {
      "entity1": 124,
      "entity2": 271
    },
    {
      "entity1": 124,
      "entity2": 40
    },
    {
      "entity1": 124,
      "entity2": 6
    },
    {
      "entity1": 124,
      "entity2": 25
    },
    {
      "entity1": 124,
      "entity2": 2
    },
    {
      "entity1": 125,
      "entity2": 205
    },
    {
      "entity1": 125,
      "entity2": 247
    },
    {
      "entity1": 125,
      "entity2": 139
    },
    {
      "entity1": 125,
      "entity2": 229
    },
    {
      "entity1": 125,
      "entity2": 106
    },
    {
      "entity1": 126,
      "entity2": 288
    },
    {
      "entity1": 128,
      "entity2": 144
    },
    {
      "entity1": 128,
      "entity2": 162
    },
    {
      "entity1": 129,
      "entity2": 110
    },
    {
      "entity1": 129,
      "entity2": 78
    },
    {
      "entity1": 130,
      "entity2": 32
    },
    {
      "entity1": 131,
      "entity2": 167
    },
    {
      "entity1": 131,
      "entity2": 35
    },
    {
      "entity1": 132,
      "entity2": 236
    },
    {
      "entity1": 132,
      "entity2": 74
    },
    {
      "entity1": 133,
      "entity2": 231
    },
    {
      "entity1": 133,
      "entity2": 191
    },
    {
      "entity1": 133,
      "entity2": 280
    },
    {
      "entity1": 133,
      "entity2": 240
    },
    {
      "entity1": 133,
      "entity2": 113
    },
    {
      "entity1": 134,
      "entity2": 135
    },
    {
      "entity1": 134,
      "entity2": 27
    },
    {
      "entity1": 135,
      "entity2": 134
    },
    {
      "entity1": 135,
      "entity2": 27
    },
    {
      "entity1": 136,
      "entity2": 182
    },
    {
      "entity1": 136,
      "entity2": 220
    },
    {
      "entity1": 136,
      "entity2": 284
    },
    {
      "entity1": 136,
      "entity2": 48
    },
    {
      "entity1": 136,
      "entity2": 36
    },
    {
      "entity1": 136,
      "entity2": 13
    },
    {
      "entity1": 137,
      "entity2": 155
    },
    {
      "entity1": 137,
      "entity2": 281
    },
    {
      "entity1": 138,
      "entity2": 153
    },
    {
      "entity1": 138,
      "entity2": 200
    },
    {
      "entity1": 138,
      "entity2": 147
    },
    {
      "entity1": 139,
      "entity2": 125
    },
    {
      "entity1": 139,
      "entity2": 247
    },
    {
      "entity1": 139,
      "entity2": 205
    },
    {
      "entity1": 139,
      "entity2": 229
    },
    {
      "entity1": 139,
      "entity2": 106
    },
    {
      "entity1": 140,
      "entity2": 196
    },
    {
      "entity1": 140,
      "entity2": 11
    },
    {
      "entity1": 141,
      "entity2": 297
    },
    {
      "entity1": 141,
      "entity2": 76
    },
    {
      "entity1": 141,
      "entity2": 60
    },
    {
      "entity1": 142,
      "entity2": 187
    },
    {
      "entity1": 142,
      "entity2": 52
    },
    {
      "entity1": 143,
      "entity2": 28
    },
    {
      "entity1": 144,
      "entity2": 128
    },
    {
      "entity1": 144,
      "entity2": 162
    },
    {
      "entity1": 145,
      "entity2": 178
    },
    {
      "entity1": 145,
      "entity2": 264
    },
    {
      "entity1": 146,
      "entity2": 292
    },
    {
      "entity1": 147,
      "entity2": 138
    },
    {
      "entity1": 147,
      "entity2": 200
    },
    {
      "entity1": 148,
      "entity2": 183
    },
    {
      "entity1": 148,
      "entity2": 121
    },
    {
      "entity1": 149,
      "entity2": 268
    },
    {
      "entity1": 149,
      "entity2": 77
    },
    {
      "entity1": 150,
      "entity2": 169
    },
    {
      "entity1": 150,
      "entity2": 181
    },
    {
      "entity1": 150,
      "entity2": 245
    },
    {
      "entity1": 150,
      "entity2": 184
    },
    {
      "entity1": 150,
      "entity2": 251
    },
    {
      "entity1": 150,
      "entity2": 95
    },
    {
      "entity1": 151,
      "entity2": 270
    },
    {
      "entity1": 153,
      "entity2": 138
    },
    {
      "entity1": 153,
      "entity2": 280
    },
    {
      "entity1": 153,
      "entity2": 200
    },
    {
      "entity1": 154,
      "entity2": 230
    },
    {
      "entity1": 154,
      "entity2": 72
    },
    {
      "entity1": 155,
      "entity2": 281
    },
    {
      "entity1": 155,
      "entity2": 137
    },
    {
      "entity1": 157,
      "entity2": 94
    },
    {
      "entity1": 158,
      "entity2": 175
    },
    {
      "entity1": 160,
      "entity2": 248
    },
    {
      "entity1": 161,
      "entity2": 207
    },
    {
      "entity1": 161,
      "entity2": 228
    },
    {
      "entity1": 161,
      "entity2": 261
    },
    {
      "entity1": 161,
      "entity2": 122
    },
    {
      "entity1": 161,
      "entity2": 20
    },
    {
      "entity1": 161,
      "entity2": 107
    },
    {
      "entity1": 161,
      "entity2": 68
    },
    {
      "entity1": 162,
      "entity2": 144
    },
    {
      "entity1": 162,
      "entity2": 128
    },
    {
      "entity1": 165,
      "entity2": 100
    },
    {
      "entity1": 165,
      "entity2": 103
    },
    {
      "entity1": 165,
      "entity2": 31
    },
    {
      "entity1": 166,
      "entity2": 47
    },
    {
      "entity1": 167,
      "entity2": 131
    },
    {
      "entity1": 167,
      "entity2": 35
    },
    {
      "entity1": 169,
      "entity2": 181
    },
    {
      "entity1": 169,
      "entity2": 184
    },
    {
      "entity1": 169,
      "entity2": 245
    },
    {
      "entity1": 169,
      "entity2": 251
    },
    {
      "entity1": 169,
      "entity2": 150
    },
    {
      "entity1": 169,
      "entity2": 95
    },
    {
      "entity1": 170,
      "entity2": 176
    },
    {
      "entity1": 171,
      "entity2": 18
    },
    {
      "entity1": 174,
      "entity2": 89
    },
    {
      "entity1": 175,
      "entity2": 158
    },
    {
      "entity1": 176,
      "entity2": 170
    },
    {
      "entity1": 176,
      "entity2": 296
    },
    {
      "entity1": 177,
      "entity2": 217
    },
    {
      "entity1": 177,
      "entity2": 45
    },
    {
      "entity1": 178,
      "entity2": 264
    },
    {
      "entity1": 178,
      "entity2": 145
    },
    {
      "entity1": 179,
      "entity2": 63
    },
    {
      "entity1": 179,
      "entity2": 64
    },
    {
      "entity1": 181,
      "entity2": 169
    },
    {
      "entity1": 181,
      "entity2": 184
    },
    {
      "entity1": 181,
      "entity2": 245
    },
    {
      "entity1": 181,
      "entity2": 251
    },
    {
      "entity1": 181,
      "entity2": 150
    },
    {
      "entity1": 181,
      "entity2": 95
    },
    {
      "entity1": 182,
      "entity2": 220
    },
    {
      "entity1": 182,
      "entity2": 284
    },
    {
      "entity1": 182,
      "entity2": 136
    },
    {
      "entity1": 182,
      "entity2": 48
    },
    {
      "entity1": 182,
      "entity2": 36
    },
    {
      "entity1": 182,
      "entity2": 13
    },
    {
      "entity1": 183,
      "entity2": 148
    },
    {
      "entity1": 184,
      "entity2": 169
    },
    {
      "entity1": 184,
      "entity2": 181
    },
    {
      "entity1": 184,
      "entity2": 245
    },
    {
      "entity1": 184,
      "entity2": 251
    },
    {
      "entity1": 184,
      "entity2": 282
    },
    {
      "entity1": 184,
      "entity2": 150
    },
    {
      "entity1": 184,
      "entity2": 95
    },
    {
      "entity1": 185,
      "entity2": 289
    },
    {
      "entity1": 185,
      "entity2": 123
    },
    {
      "entity1": 185,
      "entity2": 34
    },
    {
      "entity1": 185,
      "entity2": 110
    },
    {
      "entity1": 186,
      "entity2": 33
    },
    {
      "entity1": 187,
      "entity2": 142
    },
    {
      "entity1": 187,
      "entity2": 52
    },
    {
      "entity1": 188,
      "entity2": 279
    },
    {
      "entity1": 189,
      "entity2": 208
    },
    {
      "entity1": 189,
      "entity2": 209
    },
    {
      "entity1": 189,
      "entity2": 216
    },
    {
      "entity1": 189,
      "entity2": 265
    },
    {
      "entity1": 190,
      "entity2": 257
    },
    {
      "entity1": 190,
      "entity2": 75
    },
    {
      "entity1": 190,
      "entity2": 22
    },
    {
      "entity1": 190,
      "entity2": 85
    },
    {
      "entity1": 191,
      "entity2": 231
    },
    {
      "entity1": 191,
      "entity2": 240
    },
    {
      "entity1": 191,
      "entity2": 133
    },
    {
      "entity1": 191,
      "entity2": 93
    },
    {
      "entity1": 192,
      "entity2": 73
    },
    {
      "entity1": 193,
      "entity2": 227
    },
    {
      "entity1": 193,
      "entity2": 105
    },
    {
      "entity1": 194,
      "entity2": 210
    },
    {
      "entity1": 194,
      "entity2": 112
    },
    {
      "entity1": 196,
      "entity2": 198
    },
    {
      "entity1": 196,
      "entity2": 256
    },
    {
      "entity1": 196,
      "entity2": 140
    },
    {
      "entity1": 198,
      "entity2": 196
    },
    {
      "entity1": 198,
      "entity2": 249
    },
    {
      "entity1": 200,
      "entity2": 153
    },
    {
      "entity1": 200,
      "entity2": 138
    },
    {
      "entity1": 200,
      "entity2": 147
    },
    {
      "entity1": 200,
      "entity2": 47
    },
    {
      "entity1": 201,
      "entity2": 9
    },
    {
      "entity1": 202,
      "entity2": 237
    },
    {
      "entity1": 202,
      "entity2": 263
    },
    {
      "entity1": 203,
      "entity2": 31
    },
    {
      "entity1": 204,
      "entity2": 85
    },
    {
      "entity1": 205,
      "entity2": 229
    },
    {
      "entity1": 205,
      "entity2": 247
    },
    {
      "entity1": 205,
      "entity2": 125
    },
    {
      "entity1": 205,
      "entity2": 139
    },
    {
      "entity1": 205,
      "entity2": 106
    },
    {
      "entity1": 206,
      "entity2": 29
    },
    {
      "entity1": 207,
      "entity2": 161
    },
    {
      "entity1": 207,
      "entity2": 122
    },
    {
      "entity1": 207,
      "entity2": 71
    },
    {
      "entity1": 207,
      "entity2": 20
    },
    {
      "entity1": 207,
      "entity2": 107
    },
    {
      "entity1": 208,
      "entity2": 189
    },
    {
      "entity1": 208,
      "entity2": 216
    },
    {
      "entity1": 208,
      "entity2": 232
    },
    {
      "entity1": 208,
      "entity2": 235
    },
    {
      "entity1": 208,
      "entity2": 265
    },
    {
      "entity1": 208,
      "entity2": 266
    },
    {
      "entity1": 209,
      "entity2": 189
    },
    {
      "entity1": 209,
      "entity2": 265
    },
    {
      "entity1": 210,
      "entity2": 194
    },
    {
      "entity1": 210,
      "entity2": 112
    },
    {
      "entity1": 211,
      "entity2": 215
    },
    {
      "entity1": 211,
      "entity2": 79
    },
    {
      "entity1": 212,
      "entity2": 34
    },
    {
      "entity1": 214,
      "entity2": 244
    },
    {
      "entity1": 214,
      "entity2": 293
    },
    {
      "entity1": 215,
      "entity2": 211
    },
    {
      "entity1": 216,
      "entity2": 189
    },
    {
      "entity1": 216,
      "entity2": 208
    },
    {
      "entity1": 216,
      "entity2": 232
    },
    {
      "entity1": 216,
      "entity2": 235
    },
    {
      "entity1": 216,
      "entity2": 265
    },
    {
      "entity1": 216,
      "entity2": 266
    },
    {
      "entity1": 217,
      "entity2": 177
    },
    {
      "entity1": 217,
      "entity2": 45
    },
    {
      "entity1": 218,
      "entity2": 260
    },
    {
      "entity1": 218,
      "entity2": 86
    },
    {
      "entity1": 218,
      "entity2": 8
    },
    {
      "entity1": 219,
      "entity2": 239
    },
    {
      "entity1": 219,
      "entity2": 49
    },
    {
      "entity1": 220,
      "entity2": 182
    },
    {
      "entity1": 220,
      "entity2": 284
    },
    {
      "entity1": 220,
      "entity2": 136
    },
    {
      "entity1": 220,
      "entity2": 36
    },
    {
      "entity1": 220,
      "entity2": 13
    },
    {
      "entity1": 222,
      "entity2": 275
    },
    {
      "entity1": 222,
      "entity2": 77
    },
    {
      "entity1": 223,
      "entity2": 46
    },
    {
      "entity1": 224,
      "entity2": 269
    },
    {
      "entity1": 224,
      "entity2": 22
    },
    {
      "entity1": 225,
      "entity2": 274
    },
    {
      "entity1": 225,
      "entity2": 116
    },
    {
      "entity1": 225,
      "entity2": 19
    },
    {
      "entity1": 225,
      "entity2": 43
    },
    {
      "entity1": 227,
      "entity2": 193
    },
    {
      "entity1": 227,
      "entity2": 105
    },
    {
      "entity1": 227,
      "entity2": 80
    },
    {
      "entity1": 228,
      "entity2": 161
    },
    {
      "entity1": 228,
      "entity2": 258
    },
    {
      "entity1": 228,
      "entity2": 261
    },
    {
      "entity1": 228,
      "entity2": 278
    },
    {
      "entity1": 228,
      "entity2": 20
    },
    {
      "entity1": 228,
      "entity2": 107
    },
    {
      "entity1": 228,
      "entity2": 68
    },
    {
      "entity1": 229,
      "entity2": 205
    },
    {
      "entity1": 229,
      "entity2": 247
    },
    {
      "entity1": 229,
      "entity2": 125
    },
    {
      "entity1": 229,
      "entity2": 139
    },
    {
      "entity1": 229,
      "entity2": 106
    },
    {
      "entity1": 230,
      "entity2": 154
    },
    {
      "entity1": 230,
      "entity2": 72
    },
    {
      "entity1": 230,
      "entity2": 66
    },
    {
      "entity1": 231,
      "entity2": 191
    },
    {
      "entity1": 231,
      "entity2": 133
    },
    {
      "entity1": 231,
      "entity2": 93
    },
    {
      "entity1": 231,
      "entity2": 113
    },
    {
      "entity1": 232,
      "entity2": 208
    },
    {
      "entity1": 232,
      "entity2": 216
    },
    {
      "entity1": 232,
      "entity2": 235
    },
    {
      "entity1": 232,
      "entity2": 266
    },
    {
      "entity1": 233,
      "entity2": 26
    },
    {
      "entity1": 233,
      "entity2": 33
    },
    {
      "entity1": 234,
      "entity2": 39
    },
    {
      "entity1": 234,
      "entity2": 70
    },
    {
      "entity1": 235,
      "entity2": 208
    },
    {
      "entity1": 235,
      "entity2": 216
    },
    {
      "entity1": 235,
      "entity2": 232
    },
    {
      "entity1": 235,
      "entity2": 266
    },
    {
      "entity1": 236,
      "entity2": 132
    },
    {
      "entity1": 236,
      "entity2": 74
    },
    {
      "entity1": 237,
      "entity2": 202
    },
    {
      "entity1": 237,
      "entity2": 90
    },
    {
      "entity1": 237,
      "entity2": 53
    },
    {
      "entity1": 237,
      "entity2": 111
    },
    {
      "entity1": 238,
      "entity2": 42
    },
    {
      "entity1": 239,
      "entity2": 219
    },
    {
      "entity1": 239,
      "entity2": 49
    },
    {
      "entity1": 239,
      "entity2": 56
    },
    {
      "entity1": 239,
      "entity2": 37
    },
    {
      "entity1": 239,
      "entity2": 6
    },
    {
      "entity1": 240,
      "entity2": 191
    },
    {
      "entity1": 240,
      "entity2": 133
    },
    {
      "entity1": 242,
      "entity2": 39
    },
    {
      "entity1": 242,
      "entity2": 70
    },
    {
      "entity1": 243,
      "entity2": 99
    },
    {
      "entity1": 244,
      "entity2": 214
    },
    {
      "entity1": 245,
      "entity2": 169
    },
    {
      "entity1": 245,
      "entity2": 181
    },
    {
      "entity1": 245,
      "entity2": 184
    },
    {
      "entity1": 245,
      "entity2": 251
    },
    {
      "entity1": 245,
      "entity2": 282
    },
    {
      "entity1": 245,
      "entity2": 150
    },
    {
      "entity1": 245,
      "entity2": 95
    },
    {
      "entity1": 246,
      "entity2": 262
    },
    {
      "entity1": 247,
      "entity2": 205
    },
    {
      "entity1": 247,
      "entity2": 229
    },
    {
      "entity1": 247,
      "entity2": 125
    },
    {
      "entity1": 247,
      "entity2": 139
    },
    {
      "entity1": 247,
      "entity2": 106
    },
    {
      "entity1": 248,
      "entity2": 160
    },
    {
      "entity1": 248,
      "entity2": 259
    },
    {
      "entity1": 249,
      "entity2": 198
    },
    {
      "entity1": 251,
      "entity2": 169
    },
    {
      "entity1": 251,
      "entity2": 181
    },
    {
      "entity1": 251,
      "entity2": 184
    },
    {
      "entity1": 251,
      "entity2": 245
    },
    {
      "entity1": 251,
      "entity2": 282
    },
    {
      "entity1": 251,
      "entity2": 150
    },
    {
      "entity1": 251,
      "entity2": 95
    },
    {
      "entity1": 252,
      "entity2": 89
    },
    {
      "entity1": 253,
      "entity2": 118
    },
    {
      "entity1": 253,
      "entity2": 81
    },
    {
      "entity1": 254,
      "entity2": 291
    },
    {
      "entity1": 254,
      "entity2": 294
    },
    {
      "entity1": 254,
      "entity2": 116
    },
    {
      "entity1": 254,
      "entity2": 51
    },
    {
      "entity1": 254,
      "entity2": 43
    },
    {
      "entity1": 255,
      "entity2": 277
    },
    {
      "entity1": 256,
      "entity2": 196
    },
    {
      "entity1": 256,
      "entity2": 11
    },
    {
      "entity1": 257,
      "entity2": 190
    },
    {
      "entity1": 257,
      "entity2": 75
    },
    {
      "entity1": 257,
      "entity2": 22
    },
    {
      "entity1": 258,
      "entity2": 228
    },
    {
      "entity1": 258,
      "entity2": 278
    },
    {
      "entity1": 258,
      "entity2": 107
    },
    {
      "entity1": 259,
      "entity2": 248
    },
    {
      "entity1": 260,
      "entity2": 218
    },
    {
      "entity1": 260,
      "entity2": 86
    },
    {
      "entity1": 260,
      "entity2": 8
    },
    {
      "entity1": 261,
      "entity2": 161
    },
    {
      "entity1": 261,
      "entity2": 228
    },
    {
      "entity1": 261,
      "entity2": 273
    },
    {
      "entity1": 261,
      "entity2": 20
    },
    {
      "entity1": 261,
      "entity2": 38
    },
    {
      "entity1": 261,
      "entity2": 68
    },
    {
      "entity1": 261,
      "entity2": 3
    },
    {
      "entity1": 262,
      "entity2": 246
    },
    {
      "entity1": 263,
      "entity2": 202
    },
    {
      "entity1": 263,
      "entity2": 114
    },
    {
      "entity1": 263,
      "entity2": 101
    },
    {
      "entity1": 263,
      "entity2": 0
    },
    {
      "entity1": 264,
      "entity2": 178
    },
    {
      "entity1": 264,
      "entity2": 145
    },
    {
      "entity1": 264,
      "entity2": 94
    },
    {
      "entity1": 265,
      "entity2": 189
    },
    {
      "entity1": 265,
      "entity2": 208
    },
    {
      "entity1": 265,
      "entity2": 209
    },
    {
      "entity1": 265,
      "entity2": 216
    },
    {
      "entity1": 266,
      "entity2": 208
    },
    {
      "entity1": 266,
      "entity2": 216
    },
    {
      "entity1": 266,
      "entity2": 232
    },
    {
      "entity1": 266,
      "entity2": 235
    },
    {
      "entity1": 267,
      "entity2": 7
    },
    {
      "entity1": 268,
      "entity2": 149
    },
    {
      "entity1": 268,
      "entity2": 77
    },
    {
      "entity1": 269,
      "entity2": 224
    },
    {
      "entity1": 270,
      "entity2": 151
    },
    {
      "entity1": 271,
      "entity2": 290
    },
    {
      "entity1": 271,
      "entity2": 124
    },
    {
      "entity1": 271,
      "entity2": 37
    },
    {
      "entity1": 271,
      "entity2": 6
    },
    {
      "entity1": 271,
      "entity2": 25
    },
    {
      "entity1": 271,
      "entity2": 2
    },
    {
      "entity1": 273,
      "entity2": 261
    },
    {
      "entity1": 273,
      "entity2": 38
    },
    {
      "entity1": 274,
      "entity2": 225
    },
    {
      "entity1": 275,
      "entity2": 222
    },
    {
      "entity1": 276,
      "entity2": 55
    },
    {
      "entity1": 276,
      "entity2": 10
    },
    {
      "entity1": 277,
      "entity2": 255
    },
    {
      "entity1": 278,
      "entity2": 228
    },
    {
      "entity1": 278,
      "entity2": 258
    },
    {
      "entity1": 278,
      "entity2": 122
    },
    {
      "entity1": 278,
      "entity2": 107
    },
    {
      "entity1": 279,
      "entity2": 188
    },
    {
      "entity1": 280,
      "entity2": 133
    },
    {
      "entity1": 280,
      "entity2": 153
    },
    {
      "entity1": 280,
      "entity2": 113
    },
    {
      "entity1": 281,
      "entity2": 155
    },
    {
      "entity1": 281,
      "entity2": 137
    },
    {
      "entity1": 282,
      "entity2": 184
    },
    {
      "entity1": 282,
      "entity2": 245
    },
    {
      "entity1": 282,
      "entity2": 251
    },
    {
      "entity1": 282,
      "entity2": 95
    },
    {
      "entity1": 283,
      "entity2": 91
    },
    {
      "entity1": 284,
      "entity2": 182
    },
    {
      "entity1": 284,
      "entity2": 220
    },
    {
      "entity1": 284,
      "entity2": 136
    },
    {
      "entity1": 284,
      "entity2": 36
    },
    {
      "entity1": 284,
      "entity2": 13
    },
    {
      "entity1": 286,
      "entity2": 12
    },
    {
      "entity1": 286,
      "entity2": 5
    },
    {
      "entity1": 287,
      "entity2": 112
    },
    {
      "entity1": 288,
      "entity2": 126
    },
    {
      "entity1": 289,
      "entity2": 185
    },
    {
      "entity1": 289,
      "entity2": 123
    },
    {
      "entity1": 289,
      "entity2": 34
    },
    {
      "entity1": 289,
      "entity2": 110
    },
    {
      "entity1": 290,
      "entity2": 271
    },
    {
      "entity1": 290,
      "entity2": 124
    },
    {
      "entity1": 290,
      "entity2": 40
    },
    {
      "entity1": 290,
      "entity2": 6
    },
    {
      "entity1": 290,
      "entity2": 25
    },
    {
      "entity1": 290,
      "entity2": 2
    },
    {
      "entity1": 291,
      "entity2": 254
    },
    {
      "entity1": 291,
      "entity2": 294
    },
    {
      "entity1": 291,
      "entity2": 21
    },
    {
      "entity1": 291,
      "entity2": 51
    },
    {
      "entity1": 292,
      "entity2": 146
    },
    {
      "entity1": 293,
      "entity2": 214
    },
    {
      "entity1": 294,
      "entity2": 254
    },
    {
      "entity1": 294,
      "entity2": 291
    },
    {
      "entity1": 294,
      "entity2": 21
    },
    {
      "entity1": 294,
      "entity2": 51
    },
    {
      "entity1": 295,
      "entity2": 60
    },
    {
      "entity1": 296,
      "entity2": 176
    },
    {
      "entity1": 297,
      "entity2": 141
    },
    {
      "entity1": 297,
      "entity2": 60
    }
  ]
}